{
  "data": [
    {
      "time": {
        "elapsed": 53,
        "extra": null
      },
      "team": {
        "id": 44,
        "name": "Burnley",
        "logo": "https://media.api-sports.io/football/teams/44.png"
      },
      "player": {
        "id": 19827,
        "name": "J. Cullen"
      },
      "assist": {
        "id": 575,
        "name": "Florentino"
      },
      "type": "subst",
      "detail": "Substitution 1",
      "comments": null
    },
    {
      "time": {
        "elapsed": 69,
        "extra": null
      },
      "team": {
        "id": 45,
        "name": "Everton",
        "logo": "https://media.api-sports.io/football/teams/45.png"
      },
      "player": {
        "id": 195993,
        "name": "C. Alcaraz"
      },
      "assist": {
        "id": 202854,
        "name": "M. Rohl"
      },
      "type": "subst",
      "detail": "Substitution 1",
      "comments": null
    },
    {
      "time": {
        "elapsed": 70,
        "extra": null
      },
      "team": {
        "id": 45,
        "name": "Everton",
        "logo": "https://media.api-sports.io/football/teams/45.png"
      },
      "player": {
        "id": 125743,
        "name": "Beto"
      },
      "assist": {
        "id": 343684,
        "name": "T. Barry"
      },
      "type": "subst",
      "detail": "Substitution 2",
      "comments": null
    },
    {
      "time": {
        "elapsed": 73,
        "extra": null
      },
      "team": {
        "id": 44,
        "name": "Burnley",
        "logo": "https://media.api-sports.io/football/teams/44.png"
      },
      "player": {
        "id": 22,
        "name": "J. Bruun Larsen"
      },
      "assist": {
        "id": 196855,
        "name": "J. Anthony"
      },
      "type": "subst",
      "detail": "Substitution 2",
      "comments": null
    },
    {
      "time": {
        "elapsed": 80,
        "extra": null
      },
      "team": {
        "id": 45,
        "name": "Everton",
        "logo": "https://media.api-sports.io/football/teams/45.png"
      },
      "player": {
        "id": 284500,
        "name": "Tim Iroegbunam"
      },
      "assist": {
        "id": null,
        "name": null
      },
      "type": "Card",
      "detail": "Yellow Card",
      "comments": "Foul"
    },
    {
      "time": {
        "elapsed": 86,
        "extra": null
      },
      "team": {
        "id": 45,
        "name": "Everton",
        "logo": "https://media.api-sports.io/football/teams/45.png"
      },
      "player": {
        "id": 304317,
        "name": "Tyler Dibling"
      },
      "assist": {
        "id": null,
        "name": null
      },
      "type": "Card",
      "detail": "Yellow Card",
      "comments": "Foul"
    },
    {
      "time": {
        "elapsed": 88,
        "extra": null
      },
      "team": {
        "id": 44,
        "name": "Burnley",
        "logo": "https://media.api-sports.io/football/teams/44.png"
      },
      "player": {
        "id": 138822,
        "name": "A. Broja"
      },
      "assist": {
        "id": 36927,
        "name": "Z. Flemming"
      },
      "type": "subst",
      "detail": "Substitution 3",
      "comments": null
    },
    {
      "time": {
        "elapsed": 88,
        "extra": null
      },
      "team": {
        "id": 44,
        "name": "Burnley",
        "logo": "https://media.api-sports.io/football/teams/44.png"
      },
      "player": {
        "id": 37882,
        "name": "M. Edwards"
      },
      "assist": {
        "id": 37381,
        "name": "M. Tresor Ndayishimiye"
      },
      "type": "subst",
      "detail": "Substitution 4",
      "comments": null
    },
    {
      "time": {
        "elapsed": 88,
        "extra": null
      },
      "team": {
        "id": 45,
        "name": "Everton",
        "logo": "https://media.api-sports.io/football/teams/45.png"
      },
      "player": {
        "id": 304317,
        "name": "T. Dibling"
      },
      "assist": {
        "id": 138417,
        "name": "N. Patterson"
      },
      "type": "subst",
      "detail": "Substitution 3",
      "comments": null
    }
  ],
  "meta": {
    "lastUpdatedUTC": "2026-01-14T21:37:11Z"
  }
}
