{"lastUpdatedUTC":"2025-11-08T14:54:39.166311+00:00","matches":[{"approxMinute":90,"away":{"id":66,"name":"Manchester United FC","pos":7,"score":2,"tla":"MUN"},"home":{"id":73,"name":"Tottenham Hotspur FC","pos":3,"score":2,"tla":"TOT"},"id":537893,"phase":"FT","status":"FINISHED","utcDate":"2025-11-08T12:30:00Z"},{"approxMinute":0,"away":{"id":63,"name":"Fulham FC","pos":15,"score":null,"tla":"FUL"},"home":{"id":62,"name":"Everton FC","pos":14,"score":null,"tla":"EVE"},"id":537890,"phase":"TIMED","status":"TIMED","utcDate":"2025-11-08T15:00:00Z"},{"approxMinute":0,"away":{"id":328,"name":"Burnley FC","pos":17,"score":null,"tla":"BUR"},"home":{"id":563,"name":"West Ham United FC","pos":18,"score":null,"tla":"WHU"},"id":537894,"phase":"TIMED","status":"TIMED","utcDate":"2025-11-08T15:00:00Z"},{"approxMinute":0,"away":{"id":57,"name":"Arsenal FC","pos":1,"score":null,"tla":"ARS"},"home":{"id":71,"name":"Sunderland AFC","pos":5,"score":null,"tla":"SUN"},"id":537885,"phase":"TIMED","status":"TIMED","utcDate":"2025-11-08T17:30:00Z"},{"approxMinute":0,"away":{"id":76,"name":"Wolverhampton Wanderers FC","pos":20,"score":null,"tla":"WOL"},"home":{"id":61,"name":"Chelsea FC","pos":8,"score":null,"tla":"CHE"},"id":537889,"phase":"TIMED","status":"TIMED","utcDate":"2025-11-08T20:00:00Z"}],"serverNowUTC":"2025-11-08T14:54:39.166311+00:00"}